.drone.yml
.gitignore
.travis.yml
.woodpecker.yaml
AUTHORS
CHANGES.rst
LICENSE
MANIFEST.in
README.rst
pyproject.toml
setup.cfg
setup.py
.ci/get_sundials.sh
.ci/run_ci.sh
.ci/test-case.sh
.ci/test-sdist.sh
.circleci/config.yml
conda-recipe/build.sh
conda-recipe/meta.yaml
examples/bi_dimensional.py
examples/bi_dimensional_cy.pyx
examples/pykinsol_demo.ipynb
examples/tests/test_examples.py
pykinsol/__init__.py
pykinsol/_config.py
pykinsol/_kinsol_numpy.cpp
pykinsol/_kinsol_numpy.pyx
pykinsol/_release.py
pykinsol/_util.py
pykinsol/core.py
pykinsol.egg-info/PKG-INFO
pykinsol.egg-info/SOURCES.txt
pykinsol.egg-info/dependency_links.txt
pykinsol.egg-info/requires.txt
pykinsol.egg-info/top_level.txt
pykinsol/include/kinsol_cxx.hpp
pykinsol/include/kinsol_numpy.hpp
pykinsol/include/kinsol_numpy.pxd
pykinsol/include/sundials_cxx.hpp
pykinsol/tests/__init__.py
pykinsol/tests/test_kinsol_numpy.py
scripts/check_clean_repo_on_master.sh
scripts/coverage_badge.py
scripts/dir_to_branch.sh
scripts/generate_docs.sh
scripts/grep-for-binary-data.sh
scripts/grep-for-merge-blocking-token.sh
scripts/post_release.sh
scripts/prepare_deploy.sh
scripts/rasterize.js
scripts/release.sh
scripts/render_index.sh
scripts/run_tests.sh
scripts/update-gh-pages.sh